vidurai/__init__.py
vidurai/langchain.py
vidurai/vismriti_memory.py
vidurai/api/__init__.py
vidurai/core/__init__.py
vidurai/core/active_unlearning.py
vidurai/core/data_structures_v2.py
vidurai/core/data_structures_v3.py
vidurai/core/gist_extractor.py
vidurai/core/intelligent_decay_v2.py
vidurai/core/koshas.py
vidurai/core/langchain.py
vidurai/core/memory_ledger.py
vidurai/core/passive_decay.py
vidurai/core/rl_agent_v2.py
vidurai/core/salience_classifier.py
vidurai/core/semantic_compressor_v2.py
vidurai/core/vismriti.py
vidurai/core/viveka.py
vidurai/integrations/__init__.py
vidurai/integrations/langchain.py
vidurai/wisdom/__init__.py
vidurai-1.6.0.dist-info/METADATA
vidurai-1.6.0.dist-info/WHEEL
vidurai-1.6.0.dist-info/top_level.txt
vidurai-1.6.0.dist-info/RECORD
