Metadata-Version: 2.4
Name: vidurai
Version: 1.6.0
Summary: Self-learning AI memory system with RL-based compression - Intelligence emerges from experience, not rules
Home-page: https://github.com/chandantochandan/vidurai
Author: Chandan
Author-email: yvidurai@gmail.com
Project-URL: Homepage, https://vidurai.ai
Project-URL: Documentation, https://docs.vidurai.ai
Project-URL: Source Code, https://github.com/chandantochandan/vidurai
Project-URL: Bug Tracker, https://github.com/chandantochandan/vidurai/issues
Project-URL: Discord, https://discord.gg/DHdgS8eA
Project-URL: Changelog, https://github.com/chandantochandan/vidurai/blob/main/CHANGELOG.md
Keywords: ai memory reinforcement-learning rl-agent semantic-compression llm langchain llamaindex vedantic forgetting consciousness kosha vismriti q-learning
Classifier: Development Status :: 4 - Beta
Classifier: Intended Audience :: Developers
Classifier: Topic :: Scientific/Engineering :: Artificial Intelligence
Classifier: Topic :: Software Development :: Libraries :: Python Modules
Classifier: License :: OSI Approved :: MIT License
Classifier: Programming Language :: Python :: 3
Classifier: Programming Language :: Python :: 3.8
Classifier: Programming Language :: Python :: 3.9
Classifier: Programming Language :: Python :: 3.10
Classifier: Programming Language :: Python :: 3.11
Classifier: Programming Language :: Python :: 3.12
Classifier: Operating System :: OS Independent
Requires-Python: >=3.8
Requires-Dist: loguru>=0.7.0
Provides-Extra: rl
Requires-Dist: sentence-transformers>=2.2.0; extra == "rl"
Provides-Extra: openai
Requires-Dist: openai>=1.0.0; extra == "openai"
Provides-Extra: anthropic
Requires-Dist: anthropic>=0.18.0; extra == "anthropic"
Provides-Extra: langchain
Requires-Dist: langchain>=0.1.0; extra == "langchain"
Requires-Dist: langchain-community>=0.0.1; extra == "langchain"
Provides-Extra: llamaindex
Requires-Dist: llama-index>=0.9.0; extra == "llamaindex"
Provides-Extra: all
Requires-Dist: sentence-transformers>=2.2.0; extra == "all"
Requires-Dist: openai>=1.0.0; extra == "all"
Requires-Dist: anthropic>=0.18.0; extra == "all"
Requires-Dist: langchain>=0.1.0; extra == "all"
Requires-Dist: langchain-community>=0.0.1; extra == "all"
Requires-Dist: llama-index>=0.9.0; extra == "all"
Provides-Extra: dev
Requires-Dist: pytest>=7.0.0; extra == "dev"
Requires-Dist: pytest-cov>=4.0.0; extra == "dev"
Requires-Dist: black>=23.0.0; extra == "dev"
Requires-Dist: flake8>=6.0.0; extra == "dev"
Requires-Dist: mypy>=1.0.0; extra == "dev"
Dynamic: author
Dynamic: author-email
Dynamic: classifier
Dynamic: description
Dynamic: description-content-type
Dynamic: home-page
Dynamic: keywords
Dynamic: project-url
Dynamic: provides-extra
Dynamic: requires-dist
Dynamic: requires-python
Dynamic: summary
